{
  "main": {
    "id": "eeaba1e33b8f0f0f",
    "type": "split",
    "children": [
      {
        "id": "3d969f71e639b5d7",
        "type": "tabs",
        "children": [
          {
            "id": "6652b66c858f03f9",
            "type": "leaf",
            "state": {
              "type": "bases",
              "state": {
                "file": "未命名.base",
                "viewName": "表格"
              },
              "icon": "lucide-table",
              "title": "未命名"
            }
          }
        ]
      }
    ],
    "direction": "vertical"
  },
  "left": {
    "id": "7afb8d1164319012",
    "type": "mobile-drawer",
    "children": [
      {
        "id": "e020426a0580d6fc",
        "type": "leaf",
        "state": {
          "type": "file-explorer",
          "state": {
            "sortOrder": "alphabetical",
            "autoReveal": false
          },
          "icon": "lucide-folder-closed",
          "title": "文件列表"
        }
      },
      {
        "id": "d95c1046a8c3c257",
        "type": "leaf",
        "state": {
          "type": "search",
          "state": {
            "query": "",
            "matchingCase": false,
            "explainSearch": false,
            "collapseAll": false,
            "extraContext": false,
            "sortOrder": "alphabetical"
          },
          "icon": "lucide-search",
          "title": "搜索"
        }
      },
      {
        "id": "3b39cb4c8721cebd",
        "type": "leaf",
        "state": {
          "type": "tag",
          "state": {
            "sortOrder": "frequency",
            "useHierarchy": true,
            "showSearch": false,
            "searchQuery": ""
          },
          "icon": "lucide-tags",
          "title": "标签"
        }
      },
      {
        "id": "9bdd785b80cccd79",
        "type": "leaf",
        "state": {
          "type": "all-properties",
          "state": {
            "sortOrder": "frequency",
            "showSearch": false,
            "searchQuery": ""
          },
          "icon": "lucide-archive",
          "title": "添加笔记属性"
        }
      },
      {
        "id": "594a8ab5539546e8",
        "type": "leaf",
        "state": {
          "type": "bookmarks",
          "state": {},
          "icon": "lucide-bookmark",
          "title": "书签"
        }
      }
    ],
    "currentTab": 0
  },
  "right": {
    "id": "0bdc4dfb99463b90",
    "type": "mobile-drawer",
    "children": [
      {
        "id": "64093ad74ea98705",
        "type": "leaf",
        "state": {
          "type": "backlink",
          "state": {
            "collapseAll": false,
            "extraContext": false,
            "sortOrder": "alphabetical",
            "showSearch": false,
            "searchQuery": "",
            "backlinkCollapsed": false,
            "unlinkedCollapsed": true
          },
          "icon": "links-coming-in",
          "title": "反向链接"
        }
      },
      {
        "id": "6ee5515f6116e806",
        "type": "leaf",
        "state": {
          "type": "outgoing-link",
          "state": {
            "linksCollapsed": false,
            "unlinkedCollapsed": true
          },
          "icon": "links-going-out",
          "title": "出链"
        }
      },
      {
        "id": "7dce8a2fcaadfb79",
        "type": "leaf",
        "state": {
          "type": "outline",
          "state": {
            "followCursor": false,
            "showSearch": false,
            "searchQuery": ""
          },
          "icon": "lucide-list",
          "title": "大纲"
        }
      },
      {
        "id": "44c3d30c49c556d1",
        "type": "leaf",
        "state": {
          "type": "git-view",
          "state": {},
          "icon": "git-pull-request",
          "title": "Source Control"
        }
      }
    ],
    "currentTab": 3
  },
  "left-ribbon": {
    "hiddenItems": {
      "switcher:打开快速切换": false,
      "graph:查看关系图谱": false,
      "canvas:新建白板": false,
      "daily-notes:打开/创建今天的日记": false,
      "templates:插入模板": false,
      "command-palette:打开命令面板": false,
      "bases:新建数据库": false,
      "obsidian-git:Open Git source control": false
    }
  },
  "active": "e020426a0580d6fc",
  "lastOpenFiles": [
    "未命名 1.base",
    "未命名.base",
    "未命名.canvas",
    "未命名 1.canvas",
    "Pasted image 20260407174842.png",
    "网络/ospf.md"
  ]
}